arcor2_kinect_azure/VERSION
arcor2_kinect_azure/__init__.py
arcor2_kinect_azure/exceptions.py
arcor2_kinect_azure/kinect_azure.py
arcor2_kinect_azure/py.typed
arcor2_kinect_azure/data/depth.png
arcor2_kinect_azure/data/rgb.jpg
arcor2_kinect_azure/scripts/__init__.py
arcor2_kinect_azure/scripts/kinect_azure.py
arcor2_kinect_azure-0.6.0.dist-info/METADATA
arcor2_kinect_azure-0.6.0.dist-info/WHEEL
arcor2_kinect_azure-0.6.0.dist-info/entry_points.txt
arcor2_kinect_azure-0.6.0.dist-info/namespace_packages.txt
arcor2_kinect_azure-0.6.0.dist-info/top_level.txt
arcor2_kinect_azure-0.6.0.dist-info/RECORD
