Metadata-Version: 2.1
Name: arcor2-kinect-azure
Version: 0.6.0
Summary: REST API for Kinect Azure.
Author: Robo@FIT
Author-email: imaterna@fit.vut.cz
License: LGPL
Classifier: Development Status :: 3 - Alpha
Classifier: Intended Audience :: Developers
Classifier: Topic :: Software Development :: Build Tools
Classifier: License :: OSI Approved :: GNU Lesser General Public License v3 (LGPLv3)
Classifier: Programming Language :: Python :: 3.10
Classifier: Natural Language :: English
Classifier: Topic :: Scientific/Engineering
Requires-Python: ==3.10.*
Requires-Dist: Flask (~=2.2.3)
Requires-Dist: Pillow (~=9.4.0)
Requires-Dist: arcor2 (~=1.0.0)
Requires-Dist: numpy (~=1.23.5)
Requires-Dist: pyk4a (~=1.5.0)
